[
  {
    "id": "bounty-001",
    "issue": {
      "id": 42,
      "title": "Fix login redirect bug (urgent)",
      "url": "https://github.com/nullshot/oss-maintainer/issues/42"
    },
    "pullRequest": {
      "id": 88,
      "url": "https://github.com/nullshot/oss-maintainer/pull/88",
      "author": "krishnaw",
      "merged": true
    },
    "status": "open",
    "reward": 0
  },
  {
    "id": "bounty-002",
    "issue": {
      "id": 56,
      "title": "Improve README and add contributing guidelines",
      "url": "https://github.com/nullshot/oss-maintainer/issues/56"
    },
    "pullRequest": {
      "id": 92,
      "url": "https://github.com/nullshot/oss-maintainer/pull/92",
      "author": "alice",
      "merged": false
    },
    "status": "open",
    "reward": 0
  }
]
